README.md
setup.cfg
setup.py
musclex/__init__.py
musclex/main.py
musclex/CalibrationSettings/CalibrationSettings.py
musclex/CalibrationSettings/__init__.py
musclex/csv_manager/BM_CVSManager.py
musclex/csv_manager/CP_CSVManager.py
musclex/csv_manager/DC_CSVManager.py
musclex/csv_manager/PT_CSVManager.py
musclex/csv_manager/__init__.py
musclex/modules/BioImage.py
musclex/modules/CircularProjection.py
musclex/modules/DiffractionCentroids.py
musclex/modules/ProjectionProcessor.py
musclex/modules/QF_utilities.pyx
musclex/modules/QuadrantFolder.py
musclex/modules/__init__.py
musclex/modules/setup2.py
musclex/ui/BMStartWindow.py
musclex/ui/BM_FittingTab.py
musclex/ui/BioMuscleWindow.py
musclex/ui/BlankImageSettings.py
musclex/ui/CPBatchWindow.py
musclex/ui/CPBatchWindow2.py
musclex/ui/CPImageWindow.py
musclex/ui/CircularProjectionGUI.py
musclex/ui/ImageMerger.py
musclex/ui/ProjectionBoxTab.py
musclex/ui/ProjectionTracesGUI.py
musclex/ui/QuadrantFoldingGUI.py
musclex/ui/__init__.py
musclex/ui/ddf_processor.py
musclex/ui/diffraction_centroids.py
musclex/ui/pyqt_utils.py
musclex/utils/__init__.py
musclex/utils/file_manager.py
musclex/utils/histogram_processor.py
musclex/utils/image_processor.py
musclex_p3.egg-info/PKG-INFO
musclex_p3.egg-info/SOURCES.txt
musclex_p3.egg-info/dependency_links.txt
musclex_p3.egg-info/entry_points.txt
musclex_p3.egg-info/requires.txt
musclex_p3.egg-info/top_level.txt