Metadata-Version: 1.2
Name: musclex-p3
Version: 1.7.2.2
Summary: Muscle X
Home-page: https://github.com/biocatiit/musclex/wiki
Author: Jiranun J.
Author-email: jjiratra@hawk.iit.edu
License: UNKNOWN
Keywords: musclex,biomuscle,diffraction,biocat
Platform: UNKNOWN
Classifier: Development Status :: 3 - Alpha
Classifier: Environment :: X11 Applications :: Qt
Classifier: Intended Audience :: Science/Research
Classifier: Natural Language :: English
Classifier: Operating System :: Other OS
Classifier: Programming Language :: Python :: 2.7
Classifier: Programming Language :: Python :: 3.6
Classifier: Programming Language :: Cython
Requires-Python: >=2.7.10, <=3.6
